litepolis_router_example/__init__.py
litepolis_router_example/core.py
litepolis_router_example-0.0.1.dist-info/licenses/LICENSE
litepolis_router_example-0.0.1.dist-info/METADATA
litepolis_router_example-0.0.1.dist-info/WHEEL
litepolis_router_example-0.0.1.dist-info/top_level.txt
litepolis_router_example-0.0.1.dist-info/RECORD
