Metadata-Version: 2.4
Name: litepolis-router-example
Version: 0.0.1
Summary: An example how to create API router module for LitePolis.
Home-page: https://github.com/LitePolis-router-example
Author: David
License: MIT License
License-File: LICENSE
Requires-Dist: fastapi
Dynamic: author
Dynamic: description
Dynamic: description-content-type
Dynamic: home-page
Dynamic: license
Dynamic: license-file
Dynamic: requires-dist
Dynamic: summary
